pysunrunner/Image.py
pysunrunner/Tools.py
pysunrunner/__init__.py
pysunrunner/io.py
pysunrunner/pload.py
pysunrunner/ploadparticles.py
pysunrunner/ploadparticles_v00.py
pysunrunner/pviz.py
pysunrunner-4.5.3.dist-info/LICENSE
pysunrunner-4.5.3.dist-info/METADATA
pysunrunner-4.5.3.dist-info/WHEEL
pysunrunner-4.5.3.dist-info/top_level.txt
pysunrunner-4.5.3.dist-info/RECORD
