Metadata-Version: 2.1
Name: pysunrunner
Version: 4.5.3
Summary: A package for imaging and plotting data from sunrunner simulations
Home-page: https://github.com/BadOmen59/PySunRunner
Author: Jackson Riley (pyPLUTO routines by Dr. Bhargav Vaidya)
Author-email: jriley@predsci.com
Classifier: Programming Language :: Python :: 3
Classifier: License :: OSI Approved :: MIT License
Classifier: Operating System :: OS Independent
Requires-Python: >=3.6
License-File: LICENSE
Requires-Dist: numpy ==2.0.0
Requires-Dist: matplotlib ==3.9.1
Requires-Dist: scipy ==1.14.0
Requires-Dist: pillow ==10.4.0
